waldur_site_agent_cscs_hpc_storage/__init__.py
waldur_site_agent_cscs_hpc_storage/backend.py
waldur_site_agent_cscs_hpc_storage/hpc_user_client.py
waldur_site_agent_cscs_hpc_storage/sync_script.py
waldur_site_agent_cscs_hpc_storage/waldur_storage_proxy/__init__.py
waldur_site_agent_cscs_hpc_storage/waldur_storage_proxy/config.py
waldur_site_agent_cscs_hpc_storage/waldur_storage_proxy/main.py
waldur_site_agent_cscs_hpc_storage-0.7.7.dist-info/METADATA
waldur_site_agent_cscs_hpc_storage-0.7.7.dist-info/WHEEL
waldur_site_agent_cscs_hpc_storage-0.7.7.dist-info/entry_points.txt
waldur_site_agent_cscs_hpc_storage-0.7.7.dist-info/RECORD
