Metadata-Version: 2.4
Name: waldur-site-agent-cscs-hpc-storage
Version: 0.7.7
Summary: CSCS HPC Storage plugin for Waldur Site Agent
Author-email: OpenNode Team <info@opennodecloud.com>
Requires-Python: <4,>=3.10
Requires-Dist: fastapi-keycloak-middleware>=1.3.0
Requires-Dist: fastapi[standard]>=0.115.14
Requires-Dist: httpx[socks]>=0.24.0
Requires-Dist: waldur-site-agent>=0.7.0
